[
  {
    "$type": "ModListMetadata, Wabbajack.Lib",
    "title": "Tempus Maledictum",
    "description": "This is a list I made for myself, primarily to play a lot of quest mods that I've missed out on over the years. The main attractions are obviously all the quest mods, as well as Legacy of the Dragonborn and Timelost Dwemer. I would recommend playing as the Deep Elf Race, and choosing the Chronostasis alternate start for maximum immersionnnn. But do whatever you want, I'm not your real dad.",
    "author": "Lively",
    "maintainers": [
      "github/LivelyDismay"
    ],
    "game": "skyrimspecialedition",
    "tags": [
      "Unofficial",
      "LotD",
      "Timelost Dwemer"
    ],
    "nsfw": false,
    "image_contains_title": false,
    "force_down": false,
    "links": {
      "$type": "Links, Wabbajack.Lib",
      "image": "https://raw.githubusercontent.com/LivelyDismay/Learn-To-Mod/main/wabbajack-stuff/ScreenShot75.png",
      "readme": "https://raw.githubusercontent.com/LivelyDismay/Learn-To-Mod/main/wabbajack-stuff/TempusMaledictumReadmeMain.md",
      "download": "https://authored-files.wabbajack.org/Tempus%20Maledictum.wabbajack_9ac5216d-dc8f-472c-aeae-638ed17ca878",
      "machineURL": "tempus_maledictum",
      "discordURL": "https://discord.gg/yABEjwB"
    },
    "download_metadata": {
      "$type": "DownloadMetadata, Wabbajack.Lib",
      "Hash": "TpzohqFYgNw=",
      "Size": 977075688,
      "NumberOfArchives": 953,
      "SizeOfArchives": 82890828446,
      "NumberOfInstalledFiles": 140183,
      "SizeOfInstalledFiles": 129437781310
    },
    "version": "1.0.2"
  }
]
